doit_api/__init__.py
doit_api/_version.py
doit_api/main.py
doit_api/py.typed
doit_api-0.8.0.dist-info/LICENSE
doit_api-0.8.0.dist-info/METADATA
doit_api-0.8.0.dist-info/WHEEL
doit_api-0.8.0.dist-info/top_level.txt
doit_api-0.8.0.dist-info/RECORD
